tomato_cooker/__init__.py
tomato_cooker/grill/__init__.py
tomato_cooker/grill/grill.py
tomato_cooker/models/__init__.py
tomato_cooker/models/base.py
tomato_cooker/models/cost_based/__init__.py
tomato_cooker/models/cost_based/cost_based.py
tomato_cooker/models/cost_based/model.mzn
tomato_cooker/models/tomatic/__init__.py
tomato_cooker/models/tomatic/phone_grill.mzn
tomato_cooker/models/tomatic/tomatic.py
tomato_cooker-0.4.0.dist-info/LICENSE
tomato_cooker-0.4.0.dist-info/METADATA
tomato_cooker-0.4.0.dist-info/WHEEL
tomato_cooker-0.4.0.dist-info/top_level.txt
tomato_cooker-0.4.0.dist-info/zip-safe
tomato_cooker-0.4.0.dist-info/RECORD
